apias/__init__.py
apias/apias.py
apias-0.1.4.dist-info/LICENSE
apias-0.1.4.dist-info/METADATA
apias-0.1.4.dist-info/WHEEL
apias-0.1.4.dist-info/entry_points.txt
apias-0.1.4.dist-info/top_level.txt
apias-0.1.4.dist-info/RECORD
