Metadata-Version: 2.1
Name: apias
Version: 0.1.4
Summary: AI powered API documentation scraper and converter
Home-page: https://github.com/Emasoft/apias
Author: Emanuele Sabetta
Author-email: Emanuele Sabetta <713559+Emasoft@users.noreply.github.com>
License: MIT
Project-URL: Homepage, https://github.com/Emasoft/apias
Project-URL: Documentation, https://github.com/Emasoft/apias/docs
Project-URL: Repository, https://github.com/Emasoft/apias.git
Project-URL: Changelog, https://github.com/Emasoft/apias/blob/main/CHANGELOG.md
Classifier: Development Status :: 3 - Alpha
Classifier: Intended Audience :: Developers
Classifier: License :: OSI Approved :: MIT License
Classifier: Operating System :: OS Independent
Classifier: Programming Language :: Python :: 3
Classifier: Programming Language :: Python :: 3.9
Classifier: Programming Language :: Python :: 3.10
Classifier: Programming Language :: Python :: 3.11
Requires-Python: >=3.9
License-File: LICENSE
Requires-Dist: requests>=2.31.0
Requires-Dist: beautifulsoup4>=4.12.0
Requires-Dist: lxml>=4.9.0
Requires-Dist: tenacity>=8.2.0
Requires-Dist: playwright>=1.39.0
Requires-Dist: types-requests>=2.31.0
Requires-Dist: types-beautifulsoup4>=4.12.0
Provides-Extra: dev
Requires-Dist: black>=23.0; extra == "dev"
Requires-Dist: isort>=5.12; extra == "dev"
Requires-Dist: mypy>=1.0; extra == "dev"
Requires-Dist: ruff>=0.1; extra == "dev"
Requires-Dist: pre-commit>=3.3; extra == "dev"
Provides-Extra: docs
Requires-Dist: sphinx>=7.0; extra == "docs"
Requires-Dist: sphinx-rtd-theme>=1.3; extra == "docs"
Requires-Dist: myst-parser>=2.0; extra == "docs"
Provides-Extra: test
Requires-Dist: pytest>=7.0; extra == "test"
Requires-Dist: pytest-cov>=4.0; extra == "test"
Requires-Dist: pytest-mock>=3.10; extra == "test"
Requires-Dist: tox>=4.0; extra == "test"
